odoo/addons/stock_reception_discrepancy_distribution/README.rst
odoo/addons/stock_reception_discrepancy_distribution/__init__.py
odoo/addons/stock_reception_discrepancy_distribution/__manifest__.py
odoo/addons/stock_reception_discrepancy_distribution/i18n/es.po
odoo/addons/stock_reception_discrepancy_distribution/i18n/it.po
odoo/addons/stock_reception_discrepancy_distribution/i18n/stock_reception_discrepancy_distribution.pot
odoo/addons/stock_reception_discrepancy_distribution/models/__init__.py
odoo/addons/stock_reception_discrepancy_distribution/models/stock_move.py
odoo/addons/stock_reception_discrepancy_distribution/readme/CONTRIBUTORS.rst
odoo/addons/stock_reception_discrepancy_distribution/readme/DESCRIPTION.rst
odoo/addons/stock_reception_discrepancy_distribution/readme/USAGE.rst
odoo/addons/stock_reception_discrepancy_distribution/security/ir.model.access.csv
odoo/addons/stock_reception_discrepancy_distribution/static/description/icon.png
odoo/addons/stock_reception_discrepancy_distribution/static/description/index.html
odoo/addons/stock_reception_discrepancy_distribution/tests/__init__.py
odoo/addons/stock_reception_discrepancy_distribution/tests/test_stock_reception_discrepancy_distribution.py
odoo/addons/stock_reception_discrepancy_distribution/views/stock_picking_views.xml
odoo/addons/stock_reception_discrepancy_distribution/wizards/__init__.py
odoo/addons/stock_reception_discrepancy_distribution/wizards/stock_reception_discrepancy_distribution_views.xml
odoo/addons/stock_reception_discrepancy_distribution/wizards/stock_reception_discrepancy_distribution_wiz.py
odoo_addon_stock_reception_discrepancy_distribution-15.0.1.0.1.dist-info/METADATA
odoo_addon_stock_reception_discrepancy_distribution-15.0.1.0.1.dist-info/WHEEL
odoo_addon_stock_reception_discrepancy_distribution-15.0.1.0.1.dist-info/top_level.txt
odoo_addon_stock_reception_discrepancy_distribution-15.0.1.0.1.dist-info/RECORD
